jd_page_parser/VERSION
jd_page_parser/__init__.py
jd_page_parser/category_parsers.py
jd_page_parser/detail_parsers.py
jd_page_parser/product_list_parsers.py
tests/__init__.py
tests/conftest.py
tests/test_book_category_parser.py
tests/test_book_detail_parser.py
tests/test_book_list_parser.py
jd_page_parser-0.0.1.dist-info/METADATA
jd_page_parser-0.0.1.dist-info/WHEEL
jd_page_parser-0.0.1.dist-info/top_level.txt
jd_page_parser-0.0.1.dist-info/RECORD
